{
  "items": [
    {
      "id": "BoaWJaIWZlE",
      "title": "রমাদানে ৭টি করণীয় এবং ৭টি বজর্নীয় | মিজানুর রহমান আজহারি | চাঁপাইনবাবগঞ্জ, রাজশাহী",
      "thumbnail": "https://i.ytimg.com/vi/BoaWJaIWZlE/hqdefault.jpg"
    },
    {
      "id": "tDaWB2iILJs",
      "title": "ইসলামের ১০টি মৌলিক মূল্যবোধ | মিজানুর রহমান আজহারি | সার্কিট হাউজ মাঠ, ময়মনসিংহ",
      "thumbnail": "https://i.ytimg.com/vi/tDaWB2iILJs/hqdefault.jpg"
    },
    {
      "id": "2MPqahLpBZw",
      "title": "আল্লাহর ১৪টি গুণবাচক নাম | মিজানুর রহমান আজহারি | নবাবগঞ্জ, ঢাকা",
      "thumbnail": "https://i.ytimg.com/vi/2MPqahLpBZw/hqdefault.jpg"
    },
    {
      "id": "etXKIKVmBTg",
      "title": "মানবিক সমাজ বিনির্মাণে কুরআনের রুপরেখা | মিজানুর রহমান আজহারি",
      "thumbnail": "https://i.ytimg.com/vi/etXKIKVmBTg/hqdefault.jpg"
    },
    {
      "id": "VJaz-GOhoPE",
      "title": "বিপদে পড়লে যে দুআগুলো পড়তে হয় | মিজানুর রহমান আজহারি",
      "thumbnail": "https://i.ytimg.com/vi/VJaz-GOhoPE/hqdefault.jpg"
    },
    {
      "id": "ZleL9L05VvE",
      "title": "শান্তিপূর্ণ সহাবস্থান | মিজানুর রহমান আজহারি | Peaceful Coexistence",
      "thumbnail": "https://i.ytimg.com/vi/ZleL9L05VvE/hqdefault.jpg"
    },
    {
      "id": "HHqDd6JryKE",
      "title": "সূরা আল-আহযাবের ৪৫ এবং ৪৬ আয়াতের তাফসির | রাসূল ‎ﷺ এর পাঁচটি বৈশিষ্ট্য",
      "thumbnail": "https://i.ytimg.com/vi/HHqDd6JryKE/hqdefault.jpg"
    },
    {
      "id": "QFwJ1MkBlpg",
      "title": "মানবসম্পদ উন্নয়ন | Human Resource Development | মিজানুর রহমান আজহারি",
      "thumbnail": "https://i.ytimg.com/vi/QFwJ1MkBlpg/hqdefault.jpg"
    },
    {
      "id": "Hkj5zCyG-ig",
      "title": "জাতীয় ঐক্যের আহ্বান | মিজানুর রহমান আজহারি",
      "thumbnail": "https://i.ytimg.com/vi/Hkj5zCyG-ig/hqdefault.jpg"
    }
  ]
}